{"FEA task": [{"Product information": [{"Equipment name": ["pressure vessel"], "Part name": ["round tube"], "Design requirement": ["none"]}], "Analysis aim": ["stress analysis"], "Material and physical data": [{"Material designation": ["20# Steel"], "Material property": ["elasticity modulus ", "poisson's ratio", "yield strength", "tensile strength", "density", "specific heat capacity"]}], "Working condition": [{"Design condition": ["none"], "Operation condition": ["Inlet flow rate", "Inlet pressure", "water", "Inlet temperature"]}]}]}